camomilla/__init__.py
camomilla/apps.py
camomilla/authentication.py
camomilla/context_processors.py
camomilla/defaults.py
camomilla/dynamic_pages_urls.py
camomilla/exceptions.py
camomilla/model_api.py
camomilla/parsers.py
camomilla/permissions.py
camomilla/redirects.py
camomilla/settings.py
camomilla/sitemap.py
camomilla/translation.py
camomilla/urls.py
camomilla/contrib/__init__.py
camomilla/contrib/modeltranslation/__init__.py
camomilla/contrib/modeltranslation/hvad_migration.py
camomilla/fields/__init__.py
camomilla/fields/json.py
camomilla/management/__init__.py
camomilla/management/commands/__init__.py
camomilla/management/commands/regenerate_thumbnails.py
camomilla/managers/__init__.py
camomilla/managers/pages.py
camomilla/models/__init__.py
camomilla/models/article.py
camomilla/models/content.py
camomilla/models/media.py
camomilla/models/menu.py
camomilla/models/page.py
camomilla/models/mixins/__init__.py
camomilla/openapi/__init__.py
camomilla/openapi/schema.py
camomilla/serializers/__init__.py
camomilla/serializers/article.py
camomilla/serializers/content_type.py
camomilla/serializers/media.py
camomilla/serializers/menu.py
camomilla/serializers/page.py
camomilla/serializers/user.py
camomilla/serializers/utils.py
camomilla/serializers/validators.py
camomilla/serializers/base/__init__.py
camomilla/serializers/fields/__init__.py
camomilla/serializers/fields/file.py
camomilla/serializers/fields/related.py
camomilla/serializers/mixins/__init__.py
camomilla/serializers/mixins/fields.py
camomilla/serializers/mixins/filter_fields.py
camomilla/serializers/mixins/json.py
camomilla/serializers/mixins/language.py
camomilla/serializers/mixins/nesting.py
camomilla/serializers/mixins/optimize.py
camomilla/serializers/mixins/ordering.py
camomilla/serializers/mixins/page.py
camomilla/serializers/mixins/translation.py
camomilla/storages/__init__.py
camomilla/storages/default.py
camomilla/storages/optimize.py
camomilla/storages/overwrite.py
django_camomilla_cms-6.3.0.dist-info/licenses/LICENSE
django_camomilla_cms-6.3.0.dist-info/METADATA
django_camomilla_cms-6.3.0.dist-info/WHEEL
django_camomilla_cms-6.3.0.dist-info/top_level.txt
django_camomilla_cms-6.3.0.dist-info/RECORD
