Metadata-Version: 2.4
Name: django-camomilla-cms
Version: 6.3.0
Summary: Django powered cms
Author-email: Lotrèk <dimmitutto@lotrek.it>
License: MIT
Project-URL: Homepage, https://github.com/camomillacms/camomilla-core
Keywords: cms,django,api cms
Classifier: Development Status :: 5 - Production/Stable
Classifier: Environment :: Web Environment
Classifier: Intended Audience :: Developers
Classifier: Operating System :: OS Independent
Classifier: Programming Language :: Python
Classifier: Programming Language :: Python :: 3
Classifier: Programming Language :: Python :: 3.10
Classifier: Programming Language :: Python :: 3.11
Classifier: Programming Language :: Python :: 3.12
Classifier: Programming Language :: Python :: 3.13
Classifier: Programming Language :: Python :: 3.14
Classifier: Framework :: Django
Classifier: Framework :: Django :: 4.2
Classifier: Framework :: Django :: 5.0
Classifier: Framework :: Django :: 5.1
Classifier: Framework :: Django :: 5.2
Classifier: Framework :: Wagtail
Classifier: Topic :: Internet :: WWW/HTTP :: Site Management
Requires-Python: <3.15,>=3.10
License-File: LICENSE
Requires-Dist: Django>=4.2
Requires-Dist: django-modeltranslation<0.20.0,>=0.19.17
Requires-Dist: djsuperadmin<1.0.0,>=0.11
Requires-Dist: djangorestframework<3.17,>=3.10
Requires-Dist: django-structured-json-field>=1.2.0
Requires-Dist: pydantic>=2.10.3
Requires-Dist: pydantic-core>=2.27.0
Requires-Dist: Pillow<12.0.0,>=9.1.0
Requires-Dist: django-admin-interface<1.0.0,>=0.30.1
Requires-Dist: django-ckeditor<7.0.0,>=6.7
Requires-Dist: django-tinymce<5.0.0,>=4.1.0
Requires-Dist: python-magic<0.5,>=0.4
Requires-Dist: django_jsonform>=2.23
Dynamic: license-file
